llm_adapter/client.py
llm_adapter/exceptions.py
llm_adapter/core/dataclass.py
llm_adapter/llm/anthropic.py
llm_adapter/llm/base.py
llm_adapter/llm/google.py
llm_adapter/llm/openai.py
llm_adapter/rag/rag.py
llm_adapter/schemas/request.py
llm_adapter/schemas/response.py
llm_adapter/vectorstore/base.py
llm_adapter/vectorstore/chroma.py
llm_adapter/vectorstore/faiss.py
llm_adapter/vectorstore/pinecone.py
llm_adapter_service-1.0.0.dist-info/METADATA
llm_adapter_service-1.0.0.dist-info/WHEEL
llm_adapter_service-1.0.0.dist-info/top_level.txt
llm_adapter_service-1.0.0.dist-info/RECORD
