Metadata-Version: 2.4
Name: llm-adapter-service
Version: 1.0.0
Summary: A comprehensive LLM adapter service with safety checks and logging
Author-email: Annu Priya <a.priya@astreya.com>
License: MIT
Classifier: Development Status :: 4 - Beta
Classifier: Intended Audience :: Developers
Classifier: License :: OSI Approved :: MIT License
Classifier: Programming Language :: Python :: 3
Classifier: Programming Language :: Python :: 3.8
Classifier: Programming Language :: Python :: 3.9
Classifier: Programming Language :: Python :: 3.10
Classifier: Programming Language :: Python :: 3.11
Classifier: Programming Language :: Python :: 3.12
Requires-Python: >=3.8
Requires-Dist: requests>=2.32.0
Requires-Dist: pydantic>=2.11.0
Requires-Dist: httpx>=0.28.0
Requires-Dist: python-dotenv>=1.1.0
